setup.py
usefulutils/__init__.py
usefulutils/charset.py
usefulutils/dicts.py
usefulutils.egg-info/PKG-INFO
usefulutils.egg-info/SOURCES.txt
usefulutils.egg-info/dependency_links.txt
usefulutils.egg-info/not-zip-safe
usefulutils.egg-info/top_level.txt