Metadata-Version: 1.1
Name: usefulutils
Version: 0.1.2
Summary: Generally useful tools.
Home-page: https://github.com/onenameio/useful-utils
Author: Halfmoon Labs
Author-email: hello@halfmoonlabs.com
License: MIT
Keywords: dict dictionary scrub to_dict todict json
Platform: UNKNOWN
Classifier: Intended Audience :: Developers
Classifier: License :: OSI Approved :: MIT License
Classifier: Operating System :: OS Independent
Classifier: Programming Language :: Python
